twitter/__init__.py
twitter/__version__.py
twitter/account.py
twitter/constants.py
twitter/login.py
twitter/scraper.py
twitter/search.py
twitter/util.py
twitter_api_client-0.10.21.dist-info/LICENSE
twitter_api_client-0.10.21.dist-info/METADATA
twitter_api_client-0.10.21.dist-info/WHEEL
twitter_api_client-0.10.21.dist-info/top_level.txt
twitter_api_client-0.10.21.dist-info/RECORD
