Metadata-Version: 2.1
Name: twitter-api-client
Version: 0.10.21
Summary: Implementation of X/Twitter v1, v2, and GraphQL APIs.
Home-page: https://github.com/trevorhobenshield/twitter-api-client
Author: Trevor Hobenshield
Author-email: trevorhobenshield@gmail.com
License: MIT
Keywords: twitter api client async search automation bot scrape
Classifier: Environment :: Web Environment
Classifier: Intended Audience :: Developers
Classifier: Natural Language :: English
Classifier: Operating System :: Unix
Classifier: Operating System :: MacOS :: MacOS X
Classifier: Operating System :: Microsoft :: Windows
Classifier: Programming Language :: Python
Classifier: Programming Language :: Python :: 3
Classifier: Programming Language :: Python :: 3.10
Classifier: Programming Language :: Python :: 3.11
Classifier: Programming Language :: Python :: 3.12
Classifier: Topic :: Internet :: WWW/HTTP
Classifier: Topic :: Software Development :: Libraries
Classifier: Topic :: Software Development :: Libraries :: Python Modules
Requires-Python: >=3.10.10
License-File: LICENSE
Requires-Dist: aiofiles
Requires-Dist: nest-asyncio
Requires-Dist: httpx
Requires-Dist: tqdm
Requires-Dist: orjson
Requires-Dist: m3u8
Requires-Dist: websockets
Requires-Dist: uvloop ; platform_system != "Windows"
